MANIFEST.in
README.rst
requirements-dev.txt
setup.py
secretfy_config_creator.egg-info/PKG-INFO
secretfy_config_creator.egg-info/SOURCES.txt
secretfy_config_creator.egg-info/dependency_links.txt
secretfy_config_creator.egg-info/entry_points.txt
secretfy_config_creator.egg-info/requires.txt
secretfy_config_creator.egg-info/top_level.txt
secretfy_template/__init__.py
secretfy_template/__main__.py
secretfy_template/baseconfig.yaml
secretfy_template/baseconfig1.yaml
secretfy_template/config.py
secretfy_template/manager.py
secretfy_template/util.py
secretfy_template/res/example.json.mustache
secretfy_template/res/example.xml.mustache
secretfy_template/res/example.yaml.mustache
secretfy_template/res/secrets.json
secretfy_template/res/secrets.xml
secretfy_template/res/secrets.yaml
secretfy_template/secret/__init__.py
secretfy_template/secret/manager.py
secretfy_template/secret/secret.py
secretfy_template/template/__init__.py
secretfy_template/template/manager.py
secretfy_template/template/template.py
secretfy_template/test/__init__.py
secretfy_template/test/__main__.py
secretfy_template/test/test_repo_path.py